autodoc_ai/__init__.py
autodoc_ai/__main__.py
autodoc_ai/agents/__init__.py
autodoc_ai/agents/base.py
autodoc_ai/agents/code_analyst.py
autodoc_ai/agents/commit_summary.py
autodoc_ai/agents/documentation_writer.py
autodoc_ai/agents/wiki_selector.py
autodoc_ai/crews/__init__.py
autodoc_ai/crews/base.py
autodoc_ai/crews/commit_summary.py
autodoc_ai/crews/enrichment.py
autodoc_ai/crews/evaluation.py
autodoc_ai/crews/improvement.py
autodoc_ai/crews/pipeline.py
autodoc_ai/crews/wiki_selector.py
autodoc_ai/prompts/evals/api_eval.md
autodoc_ai/prompts/evals/architecture_eval.md
autodoc_ai/prompts/evals/base_eval_template.md
autodoc_ai/prompts/evals/changelog_eval.md
autodoc_ai/prompts/evals/cicd_eval.md
autodoc_ai/prompts/evals/configuration_eval.md
autodoc_ai/prompts/evals/contributing_eval.md
autodoc_ai/prompts/evals/deployment_eval.md
autodoc_ai/prompts/evals/faq_eval.md
autodoc_ai/prompts/evals/home_eval.md
autodoc_ai/prompts/evals/installation_eval.md
autodoc_ai/prompts/evals/readme_eval.md
autodoc_ai/prompts/evals/security_eval.md
autodoc_ai/prompts/evals/usage_eval.md
autodoc_ai/prompts/evals/wiki_eval.md
autodoc_ai/prompts/tasks/code_analyst.md
autodoc_ai/prompts/tasks/commit_summary.md
autodoc_ai/prompts/tasks/document_evaluator.md
autodoc_ai/prompts/tasks/document_improver.md
autodoc_ai/prompts/tasks/documentation_writer.md
autodoc_ai/prompts/tasks/wiki_selector.md
autodoc_ai-3.0.0.dist-info/METADATA
autodoc_ai-3.0.0.dist-info/WHEEL
autodoc_ai-3.0.0.dist-info/entry_points.txt
autodoc_ai-3.0.0.dist-info/RECORD
