Metadata-Version: 2.4
Name: autodoc_ai
Version: 3.0.0
Summary: [DEPRECATED] AI-powered documentation generation - use GitHub Copilot or Claude Code instead
Project-URL: Homepage, https://github.com/auraz/autodoc_ai
Project-URL: Bug Tracker, https://github.com/auraz/autodoc_ai/issues
Project-URL: Documentation, https://github.com/auraz/autodoc_ai/wiki
Author-email: Oleksandr Kryklia <kryklia@gmail.com>
License-Expression: MIT
Classifier: Development Status :: 7 - Inactive
Classifier: Operating System :: OS Independent
Classifier: Programming Language :: Python :: 3
Classifier: Topic :: Software Development :: Documentation
Classifier: Topic :: Software Development :: Libraries :: Python Modules
Requires-Python: <3.13,>=3.10
Requires-Dist: autodoceval-crewai>=0.2.0
Requires-Dist: crewai>=0.121.0
Requires-Dist: openai>=1.75.0
Requires-Dist: rich>=13.9.4
Requires-Dist: tiktoken>=0.9.0
Provides-Extra: dev
Requires-Dist: coverage>=7.0.0; extra == 'dev'
Requires-Dist: pytest>=7.0.0; extra == 'dev'
Requires-Dist: ruff>=0.1.0; extra == 'dev'
